{
  "generation": 3,
  "agent_counter": 26,
  "config_mode": "random",
  "history": [
    {
      "generation": 0,
      "mode": "random",
      "agents": [
        {
          "id": 0,
          "gen": 0,
          "dev": 0.75,
          "val": 0.79,
          "parents": []
        },
        {
          "id": 7,
          "gen": 0,
          "dev": 0.71,
          "val": 0.79,
          "parents": []
        },
        {
          "id": 1,
          "gen": 0,
          "dev": 0.69,
          "val": 0.78,
          "parents": []
        },
        {
          "id": 2,
          "gen": 0,
          "dev": 0.66,
          "val": 0.78,
          "parents": []
        },
        {
          "id": 3,
          "gen": 0,
          "dev": 0.79,
          "val": 0.78,
          "parents": []
        },
        {
          "id": 5,
          "gen": 0,
          "dev": 0.72,
          "val": 0.78,
          "parents": []
        },
        {
          "id": 4,
          "gen": 0,
          "dev": 0.72,
          "val": 0.66,
          "parents": []
        },
        {
          "id": 6,
          "gen": 0,
          "dev": 0.63,
          "val": 0.59,
          "parents": []
        }
      ],
      "best_val": 0.79,
      "mean_val": 0.7438,
      "duration_sec": 668.8
    },
    {
      "generation": 1,
      "mode": "random",
      "agents": [
        {
          "id": 10,
          "gen": 0,
          "dev": 0.79,
          "val": 0.83,
          "parents": [
            0
          ]
        },
        {
          "id": 12,
          "gen": 0,
          "dev": 0.81,
          "val": 0.83,
          "parents": [
            2
          ]
        },
        {
          "id": 9,
          "gen": 0,
          "dev": 0.7,
          "val": 0.8,
          "parents": [
            0
          ]
        },
        {
          "id": 11,
          "gen": 0,
          "dev": 0.78,
          "val": 0.8,
          "parents": [
            1
          ]
        },
        {
          "id": 13,
          "gen": 0,
          "dev": 0.74,
          "val": 0.8,
          "parents": []
        },
        {
          "id": 0,
          "gen": 0,
          "dev": 0.73,
          "val": 0.79,
          "parents": []
        },
        {
          "id": 8,
          "gen": 0,
          "dev": 0.78,
          "val": 0.79,
          "parents": [
            3
          ]
        },
        {
          "id": 7,
          "gen": 0,
          "dev": 0.71,
          "val": 0.78,
          "parents": []
        }
      ],
      "best_val": 0.83,
      "mean_val": 0.8025,
      "duration_sec": 683.3
    },
    {
      "generation": 2,
      "mode": "random",
      "agents": [
        {
          "id": 12,
          "gen": 0,
          "dev": 0.82,
          "val": 0.83,
          "parents": [
            2
          ]
        },
        {
          "id": 12,
          "gen": 0,
          "dev": 0.82,
          "val": 0.83,
          "parents": [
            2
          ]
        },
        {
          "id": 10,
          "gen": 0,
          "dev": 0.78,
          "val": 0.81,
          "parents": [
            0
          ]
        },
        {
          "id": 10,
          "gen": 0,
          "dev": 0.78,
          "val": 0.81,
          "parents": [
            0
          ]
        },
        {
          "id": 10,
          "gen": 0,
          "dev": 0.78,
          "val": 0.81,
          "parents": [
            0
          ]
        },
        {
          "id": 9,
          "gen": 0,
          "dev": 0.7,
          "val": 0.81,
          "parents": [
            0
          ]
        },
        {
          "id": 14,
          "gen": 1,
          "dev": 0.78,
          "val": 0.8,
          "parents": [
            11
          ]
        },
        {
          "id": 19,
          "gen": 1,
          "dev": 0.75,
          "val": 0.79,
          "parents": []
        }
      ],
      "best_val": 0.83,
      "mean_val": 0.8113,
      "duration_sec": 672.2
    },
    {
      "generation": 3,
      "mode": "random",
      "agents": [
        {
          "id": 12,
          "gen": 0,
          "dev": 0.82,
          "val": 0.83,
          "parents": [
            2
          ]
        },
        {
          "id": 12,
          "gen": 0,
          "dev": 0.82,
          "val": 0.83,
          "parents": [
            2
          ]
        },
        {
          "id": 12,
          "gen": 0,
          "dev": 0.82,
          "val": 0.83,
          "parents": [
            2
          ]
        },
        {
          "id": 12,
          "gen": 0,
          "dev": 0.82,
          "val": 0.83,
          "parents": [
            2
          ]
        },
        {
          "id": 12,
          "gen": 0,
          "dev": 0.82,
          "val": 0.83,
          "parents": [
            2
          ]
        },
        {
          "id": 10,
          "gen": 0,
          "dev": 0.79,
          "val": 0.82,
          "parents": [
            0
          ]
        },
        {
          "id": 10,
          "gen": 0,
          "dev": 0.79,
          "val": 0.82,
          "parents": [
            0
          ]
        },
        {
          "id": 25,
          "gen": 2,
          "dev": 0.78,
          "val": 0.78,
          "parents": []
        }
      ],
      "best_val": 0.83,
      "mean_val": 0.8212,
      "duration_sec": 671.7
    }
  ],
  "population": [
    {
      "id": 12,
      "strategy_prompt": "```\nYou are an expert news categorizer tasked with assigning each article to one of these categories: World News, Sports Updates, Business Reports, and Science & Technology Articles. Your goal is to provide a concise and accurate classification based on the content’s primary focus.\n\nHere's how you should approach this task:\n\n*   **World News:**  Articles dealing with global affairs – international relations, political events, geopolitical situations, diplomacy, major countries, conflicts, human rights issues.\n*   **Sports Updates:** Articles focusing on athletic competitions – team sports (football, basketball, baseball), individual athletes, tournament results, records, training, and related news.\n*   **Business Reports:** Articles concerning financial markets, corporations, economic trends, investments, company performance, trade, and business-related developments.\n*   **Science & Technology Articles:**  Articles about scientific discoveries, technological advancements, research breakthroughs, internet trends, computer science, engineering, and space exploration.\n\nFor each article, provide *only* the name of the category to which it belongs. Accuracy is paramount.\n```",
      "generation": 0,
      "parents": [
        2
      ],
      "dev_accuracy": 0.82,
      "val_accuracy": 0.83
    },
    {
      "id": 12,
      "strategy_prompt": "```\nYou are an expert news categorizer tasked with assigning each article to one of these categories: World News, Sports Updates, Business Reports, and Science & Technology Articles. Your goal is to provide a concise and accurate classification based on the content’s primary focus.\n\nHere's how you should approach this task:\n\n*   **World News:**  Articles dealing with global affairs – international relations, political events, geopolitical situations, diplomacy, major countries, conflicts, human rights issues.\n*   **Sports Updates:** Articles focusing on athletic competitions – team sports (football, basketball, baseball), individual athletes, tournament results, records, training, and related news.\n*   **Business Reports:** Articles concerning financial markets, corporations, economic trends, investments, company performance, trade, and business-related developments.\n*   **Science & Technology Articles:**  Articles about scientific discoveries, technological advancements, research breakthroughs, internet trends, computer science, engineering, and space exploration.\n\nFor each article, provide *only* the name of the category to which it belongs. Accuracy is paramount.\n```",
      "generation": 0,
      "parents": [
        2
      ],
      "dev_accuracy": 0.82,
      "val_accuracy": 0.83
    },
    {
      "id": 12,
      "strategy_prompt": "```\nYou are an expert news categorizer tasked with assigning each article to one of these categories: World News, Sports Updates, Business Reports, and Science & Technology Articles. Your goal is to provide a concise and accurate classification based on the content’s primary focus.\n\nHere's how you should approach this task:\n\n*   **World News:**  Articles dealing with global affairs – international relations, political events, geopolitical situations, diplomacy, major countries, conflicts, human rights issues.\n*   **Sports Updates:** Articles focusing on athletic competitions – team sports (football, basketball, baseball), individual athletes, tournament results, records, training, and related news.\n*   **Business Reports:** Articles concerning financial markets, corporations, economic trends, investments, company performance, trade, and business-related developments.\n*   **Science & Technology Articles:**  Articles about scientific discoveries, technological advancements, research breakthroughs, internet trends, computer science, engineering, and space exploration.\n\nFor each article, provide *only* the name of the category to which it belongs. Accuracy is paramount.\n```",
      "generation": 0,
      "parents": [
        2
      ],
      "dev_accuracy": 0.82,
      "val_accuracy": 0.83
    },
    {
      "id": 10,
      "strategy_prompt": "**New Prompt:**\n\n“As an expert news analyst, your task is to determine the primary subject of each incoming article and assign it to one of these categories: World Affairs, Sporting Events, Financial News, or Scientific Breakthroughs. Your response should consist solely of the category name you've chosen. Accuracy is paramount – carefully consider the content of the article before assigning a category.”",
      "generation": 0,
      "parents": [
        0
      ],
      "dev_accuracy": 0.79,
      "val_accuracy": 0.82
    },
    {
      "id": 12,
      "strategy_prompt": "```\nYou are an expert news categorizer tasked with assigning each article to one of these categories: World News, Sports Updates, Business Reports, and Science & Technology Articles. Your goal is to provide a concise and accurate classification based on the content’s primary focus.\n\nHere's how you should approach this task:\n\n*   **World News:**  Articles dealing with global affairs – international relations, political events, geopolitical situations, diplomacy, major countries, conflicts, human rights issues.\n*   **Sports Updates:** Articles focusing on athletic competitions – team sports (football, basketball, baseball), individual athletes, tournament results, records, training, and related news.\n*   **Business Reports:** Articles concerning financial markets, corporations, economic trends, investments, company performance, trade, and business-related developments.\n*   **Science & Technology Articles:**  Articles about scientific discoveries, technological advancements, research breakthroughs, internet trends, computer science, engineering, and space exploration.\n\nFor each article, provide *only* the name of the category to which it belongs. Accuracy is paramount.\n```",
      "generation": 0,
      "parents": [
        2
      ],
      "dev_accuracy": 0.82,
      "val_accuracy": 0.83
    },
    {
      "id": 10,
      "strategy_prompt": "**New Prompt:**\n\n“As an expert news analyst, your task is to determine the primary subject of each incoming article and assign it to one of these categories: World Affairs, Sporting Events, Financial News, or Scientific Breakthroughs. Your response should consist solely of the category name you've chosen. Accuracy is paramount – carefully consider the content of the article before assigning a category.”",
      "generation": 0,
      "parents": [
        0
      ],
      "dev_accuracy": 0.79,
      "val_accuracy": 0.82
    },
    {
      "id": 12,
      "strategy_prompt": "```\nYou are an expert news categorizer tasked with assigning each article to one of these categories: World News, Sports Updates, Business Reports, and Science & Technology Articles. Your goal is to provide a concise and accurate classification based on the content’s primary focus.\n\nHere's how you should approach this task:\n\n*   **World News:**  Articles dealing with global affairs – international relations, political events, geopolitical situations, diplomacy, major countries, conflicts, human rights issues.\n*   **Sports Updates:** Articles focusing on athletic competitions – team sports (football, basketball, baseball), individual athletes, tournament results, records, training, and related news.\n*   **Business Reports:** Articles concerning financial markets, corporations, economic trends, investments, company performance, trade, and business-related developments.\n*   **Science & Technology Articles:**  Articles about scientific discoveries, technological advancements, research breakthroughs, internet trends, computer science, engineering, and space exploration.\n\nFor each article, provide *only* the name of the category to which it belongs. Accuracy is paramount.\n```",
      "generation": 0,
      "parents": [
        2
      ],
      "dev_accuracy": 0.82,
      "val_accuracy": 0.83
    },
    {
      "id": 25,
      "strategy_prompt": "Classify the news article into one category.\nStep 1: What is the article about? (one sentence)\nStep 2: Which domain does it belong to?\nCategories: World (politics/international), Sports (athletics/games), Business (economy/companies), Sci/Tech (technology/science)\nOutput ONLY the category name on its own line at the end.",
      "generation": 2,
      "parents": [],
      "dev_accuracy": 0.78,
      "val_accuracy": 0.78
    }
  ]
}